filmranking/__init__.py
filmranking/country_analyzes.py
filmranking/country_index.py
filmranking/director_analyzes.py
filmranking/main.py
filmranking-0.0.104.dist-info/LICENSE
filmranking-0.0.104.dist-info/METADATA
filmranking-0.0.104.dist-info/WHEEL
filmranking-0.0.104.dist-info/entry_points.txt
filmranking-0.0.104.dist-info/top_level.txt
filmranking-0.0.104.dist-info/RECORD
