Metadata-Version: 2.1
Name: filmranking
Version: 0.0.104
Summary: Final Project "FILM RANKING" for Python course mimuw
Home-page: UNKNOWN
Author: Hanna Bernikova
Author-email: <hb448385@students.mimuw.edu.pl>
License: LICENSE.txt
Platform: UNKNOWN
Classifier: License :: OSI Approved :: MIT License
Classifier: Programming Language :: Python
License-File: LICENSE
Requires-Dist: pandas
Requires-Dist: numpy
